{
  "mcpServers": {
    "supabase": {
      "command": "cmd",
      "args": ["/c","npx","-y","@supabase/mcp-server-supabase@latest"],
      "env": {
        "SUPABASE_ACCESS_TOKEN": "sbp_6926ed00b4d9a43dbd36a445a62b6c4fcf23c73d"
      }
    },
    "context7": {
      "command": "cmd",
      "args": ["/c","npx","-y","@context7/mcp-server@latest"],
      "env": {
        "CONTEXT7_API_KEY": "ctx7sk-b64a8637-97e8-48eb-b29d-e82ac2f6aede"
      }
    },
    "serena": {
      "command": "cmd",
      "args": ["/c","uvx","--from","git+https://github.com/oraios/serena","serena","start-mcp-server","--context","ide-assistant"]
    },
    "playwright": {
      "command": "cmd",
      "args": ["/c","npx","-y","@playwright/mcp@latest"]
    }
  }
}